dyncache/__init__.py
dyncache/dyncache.py
dyncache/functionhash.py
dyncache/version.py
dyncache-0.1.2.dist-info/LICENSE
dyncache-0.1.2.dist-info/METADATA
dyncache-0.1.2.dist-info/WHEEL
dyncache-0.1.2.dist-info/RECORD
