Metadata-Version: 2.1
Name: dyncache
Version: 0.1.2
Summary: Dynamic input-output caching for deterministic functions
Home-page: https://github.com/b10011/dyncache
License: MIT
Keywords: function,cache,dataset,ai,machine learning
Author: Niko Järvinen
Author-email: nbjarvinen@gmail.com
Requires-Python: >=3.5,<4.0
Classifier: Development Status :: 4 - Beta
Classifier: Intended Audience :: Developers
Classifier: License :: OSI Approved :: MIT License
Classifier: Programming Language :: Python :: 3
Classifier: Programming Language :: Python :: 3.5
Classifier: Programming Language :: Python :: 3.6
Classifier: Programming Language :: Python :: 3.7
Classifier: Programming Language :: Python :: 3.8
Classifier: Programming Language :: Python :: 3.9
Classifier: Programming Language :: Python :: 3.10
Classifier: Programming Language :: Python :: 3.11
Classifier: Programming Language :: Python :: 3.12
Classifier: Programming Language :: Python :: 3.13
Classifier: Topic :: Software Development :: Libraries
Classifier: Topic :: Utilities
Requires-Dist: click (>=7.1.1)
Requires-Dist: cloudpickle (>=1.3.0)
Project-URL: Documentation, https://dyncache.readthedocs.io/en/latest/
Project-URL: Repository, https://github.com/b10011/dyncache
